paradrop/__init__.py
paradrop/main.py
paradrop/plan_demo.py
paradrop/airshark/__init__.py
paradrop/airshark/airshark.py
paradrop/airshark/analyzer.py
paradrop/airshark/scanner.py
paradrop/airshark/spectrum_reader.py
paradrop/backend/__init__.py
paradrop/backend/airshark_api.py
paradrop/backend/airshark_ws.py
paradrop/backend/audio_api.py
paradrop/backend/auth.py
paradrop/backend/change_api.py
paradrop/backend/change_ws.py
paradrop/backend/chute_api.py
paradrop/backend/chute_log_ws.py
paradrop/backend/config_api.py
paradrop/backend/cors.py
paradrop/backend/generic_ws.py
paradrop/backend/hostapd_control.py
paradrop/backend/http_server.py
paradrop/backend/information_api.py
paradrop/backend/log_sockjs.py
paradrop/backend/network_api.py
paradrop/backend/paradrop_log_ws.py
paradrop/backend/password_api.py
paradrop/backend/password_manager.py
paradrop/backend/snapd_resource.py
paradrop/backend/ssdp_responder.py
paradrop/backend/status_sockjs.py
paradrop/backend/token_manager.py
paradrop/base/__init__.py
paradrop/base/constants.py
paradrop/base/cxbr.py
paradrop/base/exceptions.py
paradrop/base/nexus.py
paradrop/base/output.py
paradrop/base/pdutils.py
paradrop/base/settings.py
paradrop/confd/__init__.py
paradrop/confd/base.py
paradrop/confd/client.py
paradrop/confd/command.py
paradrop/confd/dhcp.py
paradrop/confd/firewall.py
paradrop/confd/main.py
paradrop/confd/manager.py
paradrop/confd/network.py
paradrop/confd/parprouted.py
paradrop/confd/qos.py
paradrop/confd/wireless.py
paradrop/core/__init__.py
paradrop/core/agent/__init__.py
paradrop/core/agent/http.py
paradrop/core/agent/provisioning.py
paradrop/core/agent/reporting.py
paradrop/core/agent/wamp_session.py
paradrop/core/agent/websocket_session.py
paradrop/core/auth/__init__.py
paradrop/core/auth/user.py
paradrop/core/chute/__init__.py
paradrop/core/chute/builder.py
paradrop/core/chute/chute.py
paradrop/core/chute/chute_storage.py
paradrop/core/chute/requests.py
paradrop/core/chute/restart.py
paradrop-0.13.2.dist-info/METADATA
paradrop-0.13.2.dist-info/WHEEL
paradrop-0.13.2.dist-info/entry_points.txt
paradrop-0.13.2.dist-info/top_level.txt
paradrop-0.13.2.dist-info/RECORD
