Metadata-Version: 2.1
Name: paradrop
Version: 0.13.2
Summary: ParaDrop wireless virtualization
Home-page: http://paradrop.org
Author: ParaDrop Labs
Author-email: UNKNOWN
License: GPL
Platform: UNKNOWN
Requires-Dist: attrs (==18.2.0)
Requires-Dist: autobahn (==18.8.1)
Requires-Dist: bcrypt (==3.1.4)
Requires-Dist: colorama (==0.3.9)
Requires-Dist: configparser (==3.7.1)
Requires-Dist: docker (==2.5.1)
Requires-Dist: enum34
Requires-Dist: future (==0.16.0)
Requires-Dist: ipaddress (>=1.0.16)
Requires-Dist: jsonpatch (==1.15)
Requires-Dist: klein (==16.12.0)
Requires-Dist: netifaces (==0.10.4)
Requires-Dist: psutil (==5.6.2)
Requires-Dist: pulsectl (==17.12.2)
Requires-Dist: pycurl
Requires-Dist: PyJWT (==1.6.4)
Requires-Dist: PyYAML (==5.1)
Requires-Dist: requests (==2.21.0)
Requires-Dist: ruamel.yaml (==0.15.60)
Requires-Dist: service-identity (==17.0.0)
Requires-Dist: six (>=1.10.0)
Requires-Dist: smokesignal (==0.7.0)
Requires-Dist: Twisted (==16.2.0)
Requires-Dist: wget (==3.2)
Requires-Dist: ruamel.ordereddict (==0.4.13) ; python_version < "3.1"
Requires-Dist: functools32 (==3.2.3.post2) ; python_version < "3.2"
